LICENSE
README.md
setup.py
ahoi/__init__.py
ahoi/__main__.py
ahoi.egg-info/PKG-INFO
ahoi.egg-info/SOURCES.txt
ahoi.egg-info/dependency_links.txt
ahoi.egg-info/requires.txt
ahoi.egg-info/top_level.txt
src/ahoi_scan.c