Metadata-Version: 2.1
Name: ahoi
Version: 0.6.1
Summary: Brute-force scan for rectangular cuts
Home-page: https://gitlab.com/nikoladze/ahoi
Author: Nikolai Hartmann
Author-email: nikoladze@posteo.de
License: UNKNOWN
Platform: UNKNOWN
Requires-Python: >2.7
License-File: LICENSE
